openbnmapi/__init__.py
openbnmapi/constants.py
openbnmapi/openbnmapi.py
openbnmapi-0.3.dist-info/METADATA
openbnmapi-0.3.dist-info/RECORD
openbnmapi-0.3.dist-info/WHEEL
openbnmapi-0.3.dist-info/top_level.txt
