Metadata-Version: 2.1
Name: openbnmapi
Version: 0.3
Summary: The unofficial Python wrapper for Bank Negara Malaysia's Open API endpoints
Home-page: https://github.com/knazran/python-openbnmapi
Author: Khairul Nazran Kamarulnizam
Author-email: khairulnazran94@gmail.com
License: MIT
Platform: UNKNOWN
Requires-Dist: pandas
Requires-Dist: requests
